[
  {
    "id": 1768368311569,
    "username": "s",
    "password": "s",
    "expiresAt": "2026-01-16T05:25:11.569Z"
  },
  {
    "id": 1768368346077,
    "username": "f",
    "password": "s",
    "expiresAt": "2026-01-16T05:25:46.077Z"
  },
  {
    "id": 1768368351281,
    "username": "fs",
    "password": "sf",
    "expiresAt": "2026-01-16T05:25:51.281Z"
  },
  {
    "id": 1768368354180,
    "username": "fss",
    "password": "sf",
    "expiresAt": "2026-01-16T05:25:54.180Z"
  },
  {
    "id": 1768368356874,
    "username": "fsss",
    "password": "sf",
    "expiresAt": "2026-01-16T05:30:32.489Z"
  },
  {
    "id": 1768368359604,
    "username": "fssss",
    "password": "sf",
    "expiresAt": "2026-01-16T06:17:15.135Z"
  },
  {
    "id": 1768368365346,
    "username": "fsssss",
    "password": "sf",
    "expiresAt": "2026-01-16T05:26:05.346Z"
  },
  {
    "id": 1768368368463,
    "username": "fssssss",
    "password": "sf",
    "expiresAt": "2026-01-16T05:26:08.463Z"
  },
  {
    "id": 1768368371860,
    "username": "fssssss",
    "password": "sf",
    "expiresAt": "2026-01-16T05:26:11.860Z"
  },
  {
    "id": 1768368378184,
    "username": "fsssssss",
    "password": "sf",
    "expiresAt": "2026-01-16T05:26:18.184Z"
  },
  {
    "id": 1768370128272,
    "username": "asdas",
    "password": "dasds",
    "expiresAt": "2026-01-26T05:55:28.272Z"
  },
  {
    "id": 1768370291262,
    "username": "sd",
    "password": "sadasd",
    "expiresAt": "2027-10-30T05:58:11.262Z"
  },
  {
    "id": 1768370307995,
    "username": "fabiano",
    "password": "73740",
    "expiresAt": "2299-10-29T05:58:27.995Z"
  },
  {
    "id": 1768370683450,
    "username": "01",
    "password": "01",
    "expiresAt": "2026-01-15T06:47:26.079Z"
  },
  {
    "id": 1768373264459,
    "username": "a",
    "password": "a",
    "expiresAt": "2026-01-16T06:47:44.459Z"
  }
]